setup.py
autohook/__init__.py
autohook/autohook.py
autohook.egg-info/PKG-INFO
autohook.egg-info/SOURCES.txt
autohook.egg-info/dependency_links.txt
autohook.egg-info/entry_points.txt
autohook.egg-info/requires.txt
autohook.egg-info/top_level.txt