Metadata-Version: 1.0
Name: autohook
Version: 1.1.0
Summary: Automatic hook configuration for multiple Mercurial repositories
Home-page: https://bitbucket.org/haard/autohook
Author: Fredrik Håård
Author-email: fredrik@haard.se
License: Do whatever you want, don't blame me
Keywords: mercurial hook api
Platform: UNKNOWN
